logos_shift_client/__init__.py
logos_shift_client/bohita.py
logos_shift_client/logos_shift.py
logos_shift_client/router.py
logos_shift-0.7.0.dist-info/LICENSE
logos_shift-0.7.0.dist-info/METADATA
logos_shift-0.7.0.dist-info/WHEEL
logos_shift-0.7.0.dist-info/top_level.txt
logos_shift-0.7.0.dist-info/RECORD
